sdwaddle/__cli__.py
sdwaddle/__init__.py
sdwaddle/_version.py
sdwaddle/conf/about/__init__.yaml
sdwaddle/py.typed
super_duper_waddle-0.1.0.dist-info/LICENSE
super_duper_waddle-0.1.0.dist-info/METADATA
super_duper_waddle-0.1.0.dist-info/WHEEL
super_duper_waddle-0.1.0.dist-info/entry_points.txt
super_duper_waddle-0.1.0.dist-info/RECORD
