Metadata-Version: 2.1
Name: super-duper-waddle
Version: 0.1.0
Summary: Super duper waddle projet
Home-page: https://entelecheia.github.io/super-duper-waddle
License: MIT
Author: Young Joon Lee
Author-email: entelecheia@hotmail.com
Requires-Python: >=3.8.1,<3.12
Classifier: License :: OSI Approved :: MIT License
Classifier: Programming Language :: Python :: 3
Classifier: Programming Language :: Python :: 3.9
Classifier: Programming Language :: Python :: 3.10
Classifier: Programming Language :: Python :: 3.11
Project-URL: Repository, https://github.com/entelecheia/super-duper-waddle
